yamlql-0.2.0.2.dist-info/licenses/LICENSE
yamlql_library/__init__.py
yamlql_library/cli.py
yamlql_library/cli_logic.py
yamlql_library/database.py
yamlql_library/llm_providers.py
yamlql_library/loader.py
yamlql_library/transformer.py
yamlql_library/utils.py
yamlql-0.2.0.2.dist-info/METADATA
yamlql-0.2.0.2.dist-info/WHEEL
yamlql-0.2.0.2.dist-info/entry_points.txt
yamlql-0.2.0.2.dist-info/top_level.txt
yamlql-0.2.0.2.dist-info/RECORD
