Metadata-Version: 2.4
Name: yamlql
Version: 0.2.0.2
Summary: Query YAML files with SQL
Author-email: Sarav <sarav@users.noreply.github.com>
Requires-Python: >=3.9
License-File: LICENSE
Requires-Dist: duckdb>=0.9.0
Requires-Dist: pyyaml>=6.0
Requires-Dist: typer>=0.9.0
Requires-Dist: pandas>=2.0.0
Requires-Dist: rich>=13.0.0
Requires-Dist: python-dotenv>=1.1.0
Requires-Dist: openai>=1.86.0
Requires-Dist: google>=3.0.0
Requires-Dist: google-generativeai>=0.8.5
Requires-Dist: urllib3<2.0
Requires-Dist: prompt-toolkit>=3.0.47
Requires-Dist: pytest>=8.4.0
Provides-Extra: dev
Requires-Dist: pytest>=7.0; extra == "dev"
Requires-Dist: mkdocs>=1.5.0; extra == "dev"
Requires-Dist: mkdocs-material>=9.0.0; extra == "dev"
Requires-Dist: pymdown-extensions>=10.0; extra == "dev"
Requires-Dist: twine>=3.4.2; extra == "dev"
Requires-Dist: wheel>=0.37.1; extra == "dev"
Requires-Dist: build>=0.7.0; extra == "dev"
Provides-Extra: nlp
Requires-Dist: python-dotenv>=1.0.0; extra == "nlp"
Requires-Dist: openai>=1.0.0; extra == "nlp"
Requires-Dist: google-generativeai>=0.5.0; extra == "nlp"
Dynamic: license-file
